class_sz_data/__init__.py
class_sz_data/class_sz_data.py
class_sz_data-0.0.14.dist-info/METADATA
class_sz_data-0.0.14.dist-info/WHEEL
class_sz_data-0.0.14.dist-info/top_level.txt
class_sz_data-0.0.14.dist-info/RECORD
